coldstream/__init__.py
coldstream/case.py
coldstream/coldstream.py
coldstream/library.py
coldstream/project.py
coldstream/rest_api.py
coldstream/user.py
pycoldstream-1.0.3.dist-info/licenses/LICENSE
pycoldstream-1.0.3.dist-info/METADATA
pycoldstream-1.0.3.dist-info/WHEEL
pycoldstream-1.0.3.dist-info/top_level.txt
pycoldstream-1.0.3.dist-info/RECORD
