Metadata-Version: 2.4
Name: pycoldstream
Version: 1.0.3
Summary: Python ColdStream REST API Wrapper
Home-page: https://github.com/diabatix/pycoldstream
Author: Diabatix
Author-email: info@diabatix.com
License: MIT License
Keywords: diabatix coldstream python api wrapper
Classifier: Programming Language :: Python
Classifier: Operating System :: OS Independent
Requires-Python: >=3.6
License-File: LICENSE
Requires-Dist: requests
Requires-Dist: setuptools
Dynamic: author
Dynamic: author-email
Dynamic: classifier
Dynamic: description
Dynamic: description-content-type
Dynamic: home-page
Dynamic: keywords
Dynamic: license
Dynamic: license-file
Dynamic: requires-dist
Dynamic: requires-python
Dynamic: summary
